battinfoconverter_backend/__init__.py
battinfoconverter_backend/auxiliary.py
battinfoconverter_backend/excel_tools.py
battinfoconverter_backend/json_convert.py
battinfoconverter_backend/json_template.py
battinfoconverter_backend-2.2.2.dist-info/licenses/LICENSE
battinfoconverter_backend-2.2.2.dist-info/METADATA
battinfoconverter_backend-2.2.2.dist-info/WHEEL
battinfoconverter_backend-2.2.2.dist-info/top_level.txt
battinfoconverter_backend-2.2.2.dist-info/RECORD
