Metadata-Version: 2.4
Name: battinfoconverter-backend
Version: 2.2.2
Summary: Backend conversion module for BattInfoConverter
Author-email: Nukorn Plainpan <nukorn.p27@gmail.com>
License: MIT
Project-URL: Homepage, https://github.com/EmpaEconversion/BattInfoConverter
Project-URL: Repository, https://github.com/EmpaEconversion/BattInfoConverter
Classifier: Programming Language :: Python :: 3
Classifier: Programming Language :: Python :: 3 :: Only
Classifier: Programming Language :: Python :: 3.10
Classifier: Programming Language :: Python :: 3.11
Classifier: Programming Language :: Python :: 3.12
Classifier: License :: OSI Approved :: MIT License
Classifier: Operating System :: OS Independent
Classifier: Intended Audience :: Science/Research
Classifier: Topic :: Scientific/Engineering
Requires-Python: >=3.10
License-File: LICENSE
Requires-Dist: pandas>=2.0
Requires-Dist: openpyxl>=3.1
Requires-Dist: simplejson
Requires-Dist: tomli
Provides-Extra: app
Requires-Dist: streamlit; extra == "app"
Provides-Extra: dev
Requires-Dist: pytest>=8.4.2; extra == "dev"
Dynamic: license-file
